openquake/gem_taxonomy_data/__init__.py
openquake/gem_taxonomy_data/classes.py
openquake/gem_taxonomy_data/data/taxonomy3.3_standard.json
openquake_gem_taxonomy_data-1.4.2.dist-info/licenses/LICENSE
openquake_gem_taxonomy_data-1.4.2.dist-info/METADATA
openquake_gem_taxonomy_data-1.4.2.dist-info/WHEEL
openquake_gem_taxonomy_data-1.4.2.dist-info/top_level.txt
openquake_gem_taxonomy_data-1.4.2.dist-info/RECORD
