Metadata-Version: 2.4
Name: openquake.gem-taxonomy-data
Version: 1.4.2
Summary: Openquake Gem Taxonomy Data - taxonomy data and python classes to access it.
Author-email: Matteo Nastasi <nastasi@openquake.org>
Maintainer-email: Matteo Nastasi <nastasi@openquake.org>
Project-URL: Repository, https://github.com/gem/oq-gem-taxonomy-data
Project-URL: Bug Tracker, https://github.com/gem/oq-gem-taxonomy-data/issues
Keywords: GEM,taxonomy,standard,openquake
Classifier: Development Status :: 4 - Beta
Classifier: Programming Language :: Python
Requires-Python: >=3
License-File: LICENSE
Provides-Extra: cli
Dynamic: license-file
